devCellPy/__init__.py
devCellPy/__main__.py
devCellPy/config.py
devCellPy/featurerank.py
devCellPy/helpers.py
devCellPy/importing_modules.py
devCellPy/layer.py
devCellPy/predict.py
devCellPy/train.py
devCellPy-1.5.0.dist-info/LICENSE.md
devCellPy-1.5.0.dist-info/METADATA
devCellPy-1.5.0.dist-info/WHEEL
devCellPy-1.5.0.dist-info/entry_points.txt
devCellPy-1.5.0.dist-info/top_level.txt
devCellPy-1.5.0.dist-info/RECORD
